Workbook

Sheet Assumptions
A1: Caddy 19 — Model Assumptions
A2: Mobile car-detailing at golf/country clubs — Dallas-Fort Worth. Edit yellow cells; every other tab recalculates.
A4: SHARED DRIVERS
A5: Avg ticket — The Turn (express) | B5: 85
A6: Avg ticket — Full Round | B6: 210
A7: Avg ticket — Championship | B7: 400
A8: Blended avg ticket | B8: 165
A9: Tech labor % of service revenue | B9: 0.32
A10: Payroll burden (employer tax + workers' comp) % of wages | B10: 0.14
A11: Credit-card processing % of revenue | B11: 0.029
A12: Club revenue share % of revenue | B12: 0.12
A13: Supplies/consumables % of revenue | B13: 0.07
A14: Vehicle lease $/month per rig | B14: 650
A15: Commercial auto insurance $/month per rig | B15: 220
A16: Fuel $/month per rig | B16: 250
A17: Equipment upkeep/replacement reserve $/month per rig | B17: 150
A19: SINGLE-CLUB DRIVERS
A20: Club-days per month | B20: 13
A21: Revenue per club-day | B21: 780
A22: GL + garagekeepers + BOP insurance $/month | B22: 150
A23: Software/booking/phone $/month | B23: 80
A24: Marketing $/month | B24: 150
A25: Misc/contingency $/month | B25: 200
A27: SCALED-DFW DRIVERS
A28: Number of clubs | B28: 10
A29: Number of rigs/crews | B29: 5
A30: Number of techs | B30: 10
A31: Revenue per club per month | B31: 9500
A32: Manager salary loaded $/year | B32: 79800
A33: GL + garagekeepers + BOP + umbrella $/month | B33: 600
A34: Software/booking/dispatch/phones $/month | B34: 500
A35: Marketing $/month | B35: 1000
A36: Accounting/admin/misc $/month | B36: 1500
A39: Legend: yellow-filled blue-text cells are editable inputs. All other cells contain formulas and recalculate automatically.

Sheet Single Club (Monthly + Annual)
A1: Caddy 19 — Single Club P&L
A2: One club, one rig/crew. Monthly and annualized owner economics.
A4: Line Item | B4: Monthly | C4: Annual
A5: Revenue | B5: =Assumptions!$B$20*Assumptions!$B$21 -> 10140 | C5: =B5*12 -> 121680
A6: Tech labor | B6: =B5*Assumptions!$B$9 -> 3244.8 | C6: =C5*Assumptions!$B$9 -> 38937.6
A7: Payroll burden | B7: =B6*Assumptions!$B$10 -> 454.272 | C7: =C6*Assumptions!$B$10 -> 5451.264
A8: Credit-card processing | B8: =B5*Assumptions!$B$11 -> 294.06 | C8: =C5*Assumptions!$B$11 -> 3528.72
A9: Club revenue share | B9: =B5*Assumptions!$B$12 -> 1216.8 | C9: =C5*Assumptions!$B$12 -> 14601.6
A10: Supplies | B10: =B5*Assumptions!$B$13 -> 709.8 | C10: =C5*Assumptions!$B$13 -> 8517.6
A11: Vehicle lease (1 rig) | B11: =Assumptions!$B$14 -> 650 | C11: =B11*12 -> 7800
A12: Commercial auto insurance (1 rig) | B12: =Assumptions!$B$15 -> 220 | C12: =B12*12 -> 2640
A13: GL/garagekeepers/BOP | B13: =Assumptions!$B$22 -> 150 | C13: =B13*12 -> 1800
A14: Fuel (1 rig) | B14: =Assumptions!$B$16 -> 250 | C14: =B14*12 -> 3000
A15: Equipment upkeep (1 rig) | B15: =Assumptions!$B$17 -> 150 | C15: =B15*12 -> 1800
A16: Software/booking/phone | B16: =Assumptions!$B$23 -> 80 | C16: =B16*12 -> 960
A17: Marketing | B17: =Assumptions!$B$24 -> 150 | C17: =B17*12 -> 1800
A18: Misc/contingency | B18: =Assumptions!$B$25 -> 200 | C18: =B18*12 -> 2400
A19: TOTAL OPERATING COSTS | B19: =SUM(B6:B18) -> 7769.732 | C19: =SUM(C6:C18) -> 93236.784
A20: OWNER CASH FLOW before tax & owner salary | B20: =B5-B19 -> 2370.268 | C20: =C5-C19 -> 28443.216
A21: Operating margin % | B21: =B20/B5 -> 0.23375424 | C21: =C20/C5 -> 0.23375424
A23: Note: Assumes Luke provides the sales/management labor (unpaid here). One club is a modest owner-operator business; scale is where the real income is.

Sheet Scaled DFW (Monthly + Annual)
A1: Caddy 19 — Scaled DFW P&L
A2: Multi-club, multi-rig operation with a manager running day-to-day. Monthly and annualized.
A4: Line Item | B4: Monthly | C4: Annual
A5: Revenue | B5: =Assumptions!$B$28*Assumptions!$B$31 -> 95000 | C5: =B5*12 -> 1140000
A6: Tech labor | B6: =B5*Assumptions!$B$9 -> 30400 | C6: =C5*Assumptions!$B$9 -> 364800
A7: Payroll burden | B7: =B6*Assumptions!$B$10 -> 4256 | C7: =C6*Assumptions!$B$10 -> 51072
A8: Manager salary | B8: =Assumptions!$B$32/12 -> 6650 | C8: =Assumptions!$B$32 -> 79800
A9: Credit-card processing | B9: =B5*Assumptions!$B$11 -> 2755 | C9: =C5*Assumptions!$B$11 -> 33060
A10: Club revenue share | B10: =B5*Assumptions!$B$12 -> 11400 | C10: =C5*Assumptions!$B$12 -> 136800
A11: Supplies | B11: =B5*Assumptions!$B$13 -> 6650 | C11: =C5*Assumptions!$B$13 -> 79800
A12: Vehicle leases | B12: =Assumptions!$B$29*Assumptions!$B$14 -> 3250 | C12: =B12*12 -> 39000
A13: Commercial auto insurance | B13: =Assumptions!$B$29*Assumptions!$B$15 -> 1100 | C13: =B13*12 -> 13200
A14: GL/garagekeepers/BOP/umbrella | B14: =Assumptions!$B$33 -> 600 | C14: =B14*12 -> 7200
A15: Fuel | B15: =Assumptions!$B$29*Assumptions!$B$16 -> 1250 | C15: =B15*12 -> 15000
A16: Equipment upkeep | B16: =Assumptions!$B$29*Assumptions!$B$17 -> 750 | C16: =B16*12 -> 9000
A17: Software/booking/dispatch/phones | B17: =Assumptions!$B$34 -> 500 | C17: =B17*12 -> 6000
A18: Marketing | B18: =Assumptions!$B$35 -> 1000 | C18: =B18*12 -> 12000
A19: Accounting/admin/misc | B19: =Assumptions!$B$36 -> 1500 | C19: =B19*12 -> 18000
A20: TOTAL OPERATING COSTS | B20: =SUM(B6:B19) -> 72061 | C20: =SUM(C6:C19) -> 864732
A21: OWNER CASH FLOW before tax | B21: =B5-B20 -> 22939 | C21: =C5-C20 -> 275268
A22: Operating margin % | B22: =B21/B5 -> 0.24146316 | C22: =C21/C5 -> 0.24146316
A24: Note: At maturity. This is owner pre-tax cash flow with a manager running day-to-day; Luke can take salary and/or distributions from it.

Sheet Startup Costs
A1: Caddy 19 — Startup Costs
A2: One-time capital required to launch a single club vs. scale to ~5 rigs / 10 clubs.
A4: SINGLE CLUB (leased vehicle) | D4: SCALE-UP (to ~5 rigs / 10 clubs)
A5: Item | B5: Cost | D5: Item | E5: Cost
A6: Detailing equipment (owned) | B6: 4000 | D6: Detailing equipment x 5 rigs | E6: 22500
A7: Water-reclamation + turf-safe gear | B7: 500 | D7: Vehicle lease drive-offs x 5 | E7: 7500
A8: Vehicle lease drive-off (1st month + deposit) | B8: 1500 | D8: Vehicle wraps x 5 (optional, after first signed club each) | E8: 12500
A9: Vehicle magnets/light branding | B9: 300 | D9: Ramp working capital / manager runway | E9: 30000
A10: Insurance down payment | B10: 600 | D10: Scheduling tool / systems | E10: 5000
A11: Brand/print/uniforms | B11: 800 | D11: Contingency | E11: 9000
A12: Website/domain/software setup | B12: 200
A13: Licenses/permits (TX sales-tax permit, city) | B13: 150
A14: Initial supplies stock | B14: 600
A15: Working capital buffer (~2 months) | B15: 4000
A16: Contingency (~10%) | B16: 1300
A17: TOTAL | B17: =SUM(B6:B16) -> 13950 | D17: TOTAL | E17: =SUM(E6:E11) -> 86500
A19: Note: Scale-up capital is best funded organically — each signed club's cash flow funds the next crew — rather than raised upfront.
