Workbook

Sheet Drivers
A1: Drivers - Platform vs. Operator Model
A2: Yellow cells are inputs (blue text). All other tabs calculate from these.
A3: PLATFORM DRIVERS | B3: Value | C3: Note
A4: Number of venues | B4: 50
A5: Avg members/users per venue | B5: 300
A6: Monthly booking rate (% of users booking/month) | B6: 0.1
A7: Avg job value ($) | B7: 130
A8: Platform take-rate (% of job value) | B8: 0.15
A9: Payment processing (% of GMV, platform's cost) | B9: 0.029
A10: Venue amenity/SaaS fee ($/month per venue) | B10: 250
A11: Providers on platform | B11: 60
A12: Provider subscription ($/month) | B12: 50
A14: PLATFORM COST DRIVERS | B14: Value | C14: Note
A15: Software/hosting/app dev & maintenance ($/mo) | B15: 6000
A16: Ops/account staff: cost per staffer ($/mo) | B16: 6000
A17: Venues covered per ops staffer | B17: 20
A18: Insurance / E&O ($/mo) | B18: 800
A19: Venue acquisition / BD ($/mo) | B19: 8000
A20: Marketing ($/mo) | B20: 2000
A21: G&A / misc ($/mo) | B21: 2000
A23: OPERATOR DRIVERS | B23: Value | C23: Note
A24: Cash flow per crew ($/mo) | B24: 5335 | C24: From the one-crew model
A25: Clubs served per crew | B25: 3
A26: Manager salary loaded ($/mo, kicks in above 3 crews) | B26: 6650
A27: Number of crews (operator scenario) | B27: 8
A29: COMPUTED | B29: Value | C29: Note
A30: Total users | B30: =B4*B5 -> 15000
A31: Monthly bookings | B31: =B30*B6 -> 1500
A32: GMV / month | B32: =B31*B7 -> 195000
A33: Ops staff needed | B33: =ROUNDUP(B4/B17,0) -> 3

Sheet Platform P&L
A1: Platform P&L (Monthly and Annual)
A3: Line item | B3: Monthly | C3: Annual
A4: Revenue
A5: Transaction revenue (GMV x take-rate) | B5: =Drivers!B32*Drivers!B8 -> 29250 | C5: =B5*12 -> 351000
A6: Venue fees | B6: =Drivers!B4*Drivers!B10 -> 12500 | C6: =B6*12 -> 150000
A7: Provider subscriptions | B7: =Drivers!B11*Drivers!B12 -> 3000 | C7: =B7*12 -> 36000
A8: TOTAL REVENUE | B8: =SUM(B5:B7) -> 44750 | C8: =B8*12 -> 537000
A9: Costs
A10: Payment processing (GMV x %) | B10: =Drivers!B32*Drivers!B9 -> 5655 | C10: =B10*12 -> 67860
A11: Software/hosting | B11: =Drivers!B15 -> 6000 | C11: =B11*12 -> 72000
A12: Ops/account staff | B12: =Drivers!B33*Drivers!B16 -> 18000 | C12: =B12*12 -> 216000
A13: Insurance/E&O | B13: =Drivers!B18 -> 800 | C13: =B13*12 -> 9600
A14: Venue acquisition/BD | B14: =Drivers!B19 -> 8000 | C14: =B14*12 -> 96000
A15: Marketing | B15: =Drivers!B20 -> 2000 | C15: =B15*12 -> 24000
A16: G&A/misc | B16: =Drivers!B21 -> 2000 | C16: =B16*12 -> 24000
A17: TOTAL COSTS | B17: =SUM(B10:B16) -> 42455 | C17: =B17*12 -> 509460
A18: PLATFORM PROFIT (pre-tax) | B18: =B8-B17 -> 2295 | C18: =B18*12 -> 27540
A19: Platform margin % | B19: =IF(B8=0,0,B18/B8) -> 0.051284916 | C19: =IF(C8=0,0,C18/C8) -> 0.051284916
A21: Memo
A22: GMV | B22: =Drivers!B32 -> 195000 | C22: =B22*12 -> 2340000
A23: Platform revenue as % of GMV (the real take) | B23: =IF(B22=0,0,B8/B22) -> 0.22948718 | C23: =B23 -> 0.22948718
A25: Note: Platforms are THIN until scale - at 50 venues this barely clears breakeven; profit scales with venue count. Watch how few crews it takes to match this on the Comparison tab.

Sheet Operator vs Platform
A1: Operator vs. Platform
A3: Operator scenario (monthly) | B3: Value
A4: Crews | B4: =Drivers!B27 -> 8
A5: Operator gross cash flow | B5: =B4*Drivers!B24 -> 42680
A6: Manager salary (one manager above 3 crews) | B6: =IF(B4>3,Drivers!B26,0) -> 6650 | C6: Simplification: one manager only; larger scale would need more.
A7: OPERATOR PROFIT / mo | B7: =B5-B6 -> 36030
A8: Clubs engaged (operator) | B8: =B4*Drivers!B25 -> 24
A10: Metric | B10: Operator | C10: Platform
A11: Venues/clubs engaged | B11: =B8 -> 24 | C11: =Drivers!B4 -> 50
A12: Monthly profit | B12: =B7 -> 36030 | C12: ='Platform P&L'!B18 -> 2295
A13: Annual profit | B13: =B12*12 -> 432360 | C13: =C12*12 -> 27540
A14: Headcount feel | B14: =B4*2&" techs"&IF(B4>3," + 1 manager","") -> 16 techs + 1 manager | C14: =Drivers!B33&" ops staff + BD" -> 3 ops staff + BD
A16: CROSSOVER
A17: Operator profit/mo at current crews | B17: =B7 -> 36030
A18: Platform profit/mo at current venues | B18: =C12 -> 2295
A19: Operator advantage (operator - platform) | B19: =B17-B18 -> 33735
A20: Result | B20: =IF(B17>B18,"OPERATOR wins at this setting: "&TEXT(B17,"$#,##0")&"/mo with "&B4&" crews vs. platform "&TEXT(B18,"$#,##0")&"/mo with "&Drivers!B4&" venues.","PLATFORM wins at this setting: "&TEXT(B18,"$#,##0")&"/mo with "&Drivers!B4&" venues vs. operator "&TEXT(B17,"$#,##0")&"/mo with "&B4&" crews.") -> OPERATOR wins at this setting: $36,030/mo with 8 crews vs. platform $2,295/mo with 50 venues.
A22: Note: At small scale, OPERATING crews earns far more per unit than platforming them - the platform only wins at large venue counts (often 100+). Operator = certain but labor-capped; platform = scalable but thin and capital/time-intensive to reach density.

Sheet Sensitivity
A1: Sensitivity - Platform Monthly Profit
A2: Live formulas; all other inputs held at Drivers values.
A4: GRID A - Platform monthly profit: Number of venues (rows) x Take-rate (cols)
A5: Venues \ Take-rate | B5: 0.1 | C5: 0.125 | D5: 0.15 | E5: 0.2 | F5: 0.25
A6: 25 | B6: =($A6*Drivers!$B$5*Drivers!$B$6*Drivers!$B$7)*(B$5-Drivers!$B$9)+$A6*Drivers!$B$10+Drivers!$B$11*Drivers!$B$12-Drivers!$B$15-ROUNDUP($A6/Drivers!$B$17,0)*Drivers!$B$16-Drivers!$B$18-Drivers!$B$19-Drivers!$B$20-Drivers!$B$21 -> -14627.5 | C6: =($A6*Drivers!$B$5*Drivers!$B$6*Drivers!$B$7)*(C$5-Drivers!$B$9)+$A6*Drivers!$B$10+Drivers!$B$11*Drivers!$B$12-Drivers!$B$15-ROUNDUP($A6/Drivers!$B$17,0)*Drivers!$B$16-Drivers!$B$18-Drivers!$B$19-Drivers!$B$20-Drivers!$B$21 -> -12190 | D6: =($A6*Drivers!$B$5*Drivers!$B$6*Drivers!$B$7)*(D$5-Drivers!$B$9)+$A6*Drivers!$B$10+Drivers!$B$11*Drivers!$B$12-Drivers!$B$15-ROUNDUP($A6/Drivers!$B$17,0)*Drivers!$B$16-Drivers!$B$18-Drivers!$B$19-Drivers!$B$20-Drivers!$B$21 -> -9752.5 | E6: =($A6*Drivers!$B$5*Drivers!$B$6*Drivers!$B$7)*(E$5-Drivers!$B$9)+$A6*Drivers!$B$10+Drivers!$B$11*Drivers!$B$12-Drivers!$B$15-ROUNDUP($A6/Drivers!$B$17,0)*Drivers!$B$16-Drivers!$B$18-Drivers!$B$19-Drivers!$B$20-Drivers!$B$21 -> -4877.5 | F6: =($A6*Drivers!$B$5*Drivers!$B$6*Drivers!$B$7)*(F$5-Drivers!$B$9)+$A6*Drivers!$B$10+Drivers!$B$11*Drivers!$B$12-Drivers!$B$15-ROUNDUP($A6/Drivers!$B$17,0)*Drivers!$B$16-Drivers!$B$18-Drivers!$B$19-Drivers!$B$20-Drivers!$B$21 -> -2.5
A7: 50 | B7: =($A7*Drivers!$B$5*Drivers!$B$6*Drivers!$B$7)*(B$5-Drivers!$B$9)+$A7*Drivers!$B$10+Drivers!$B$11*Drivers!$B$12-Drivers!$B$15-ROUNDUP($A7/Drivers!$B$17,0)*Drivers!$B$16-Drivers!$B$18-Drivers!$B$19-Drivers!$B$20-Drivers!$B$21 -> -7455 | C7: =($A7*Drivers!$B$5*Drivers!$B$6*Drivers!$B$7)*(C$5-Drivers!$B$9)+$A7*Drivers!$B$10+Drivers!$B$11*Drivers!$B$12-Drivers!$B$15-ROUNDUP($A7/Drivers!$B$17,0)*Drivers!$B$16-Drivers!$B$18-Drivers!$B$19-Drivers!$B$20-Drivers!$B$21 -> -2580 | D7: =($A7*Drivers!$B$5*Drivers!$B$6*Drivers!$B$7)*(D$5-Drivers!$B$9)+$A7*Drivers!$B$10+Drivers!$B$11*Drivers!$B$12-Drivers!$B$15-ROUNDUP($A7/Drivers!$B$17,0)*Drivers!$B$16-Drivers!$B$18-Drivers!$B$19-Drivers!$B$20-Drivers!$B$21 -> 2295 | E7: =($A7*Drivers!$B$5*Drivers!$B$6*Drivers!$B$7)*(E$5-Drivers!$B$9)+$A7*Drivers!$B$10+Drivers!$B$11*Drivers!$B$12-Drivers!$B$15-ROUNDUP($A7/Drivers!$B$17,0)*Drivers!$B$16-Drivers!$B$18-Drivers!$B$19-Drivers!$B$20-Drivers!$B$21 -> 12045 | F7: =($A7*Drivers!$B$5*Drivers!$B$6*Drivers!$B$7)*(F$5-Drivers!$B$9)+$A7*Drivers!$B$10+Drivers!$B$11*Drivers!$B$12-Drivers!$B$15-ROUNDUP($A7/Drivers!$B$17,0)*Drivers!$B$16-Drivers!$B$18-Drivers!$B$19-Drivers!$B$20-Drivers!$B$21 -> 21795
A8: 100 | B8: =($A8*Drivers!$B$5*Drivers!$B$6*Drivers!$B$7)*(B$5-Drivers!$B$9)+$A8*Drivers!$B$10+Drivers!$B$11*Drivers!$B$12-Drivers!$B$15-ROUNDUP($A8/Drivers!$B$17,0)*Drivers!$B$16-Drivers!$B$18-Drivers!$B$19-Drivers!$B$20-Drivers!$B$21 -> 6890 | C8: =($A8*Drivers!$B$5*Drivers!$B$6*Drivers!$B$7)*(C$5-Drivers!$B$9)+$A8*Drivers!$B$10+Drivers!$B$11*Drivers!$B$12-Drivers!$B$15-ROUNDUP($A8/Drivers!$B$17,0)*Drivers!$B$16-Drivers!$B$18-Drivers!$B$19-Drivers!$B$20-Drivers!$B$21 -> 16640 | D8: =($A8*Drivers!$B$5*Drivers!$B$6*Drivers!$B$7)*(D$5-Drivers!$B$9)+$A8*Drivers!$B$10+Drivers!$B$11*Drivers!$B$12-Drivers!$B$15-ROUNDUP($A8/Drivers!$B$17,0)*Drivers!$B$16-Drivers!$B$18-Drivers!$B$19-Drivers!$B$20-Drivers!$B$21 -> 26390 | E8: =($A8*Drivers!$B$5*Drivers!$B$6*Drivers!$B$7)*(E$5-Drivers!$B$9)+$A8*Drivers!$B$10+Drivers!$B$11*Drivers!$B$12-Drivers!$B$15-ROUNDUP($A8/Drivers!$B$17,0)*Drivers!$B$16-Drivers!$B$18-Drivers!$B$19-Drivers!$B$20-Drivers!$B$21 -> 45890 | F8: =($A8*Drivers!$B$5*Drivers!$B$6*Drivers!$B$7)*(F$5-Drivers!$B$9)+$A8*Drivers!$B$10+Drivers!$B$11*Drivers!$B$12-Drivers!$B$15-ROUNDUP($A8/Drivers!$B$17,0)*Drivers!$B$16-Drivers!$B$18-Drivers!$B$19-Drivers!$B$20-Drivers!$B$21 -> 65390
A9: 150 | B9: =($A9*Drivers!$B$5*Drivers!$B$6*Drivers!$B$7)*(B$5-Drivers!$B$9)+$A9*Drivers!$B$10+Drivers!$B$11*Drivers!$B$12-Drivers!$B$15-ROUNDUP($A9/Drivers!$B$17,0)*Drivers!$B$16-Drivers!$B$18-Drivers!$B$19-Drivers!$B$20-Drivers!$B$21 -> 15235 | C9: =($A9*Drivers!$B$5*Drivers!$B$6*Drivers!$B$7)*(C$5-Drivers!$B$9)+$A9*Drivers!$B$10+Drivers!$B$11*Drivers!$B$12-Drivers!$B$15-ROUNDUP($A9/Drivers!$B$17,0)*Drivers!$B$16-Drivers!$B$18-Drivers!$B$19-Drivers!$B$20-Drivers!$B$21 -> 29860 | D9: =($A9*Drivers!$B$5*Drivers!$B$6*Drivers!$B$7)*(D$5-Drivers!$B$9)+$A9*Drivers!$B$10+Drivers!$B$11*Drivers!$B$12-Drivers!$B$15-ROUNDUP($A9/Drivers!$B$17,0)*Drivers!$B$16-Drivers!$B$18-Drivers!$B$19-Drivers!$B$20-Drivers!$B$21 -> 44485 | E9: =($A9*Drivers!$B$5*Drivers!$B$6*Drivers!$B$7)*(E$5-Drivers!$B$9)+$A9*Drivers!$B$10+Drivers!$B$11*Drivers!$B$12-Drivers!$B$15-ROUNDUP($A9/Drivers!$B$17,0)*Drivers!$B$16-Drivers!$B$18-Drivers!$B$19-Drivers!$B$20-Drivers!$B$21 -> 73735 | F9: =($A9*Drivers!$B$5*Drivers!$B$6*Drivers!$B$7)*(F$5-Drivers!$B$9)+$A9*Drivers!$B$10+Drivers!$B$11*Drivers!$B$12-Drivers!$B$15-ROUNDUP($A9/Drivers!$B$17,0)*Drivers!$B$16-Drivers!$B$18-Drivers!$B$19-Drivers!$B$20-Drivers!$B$21 -> 102985
A10: 250 | B10: =($A10*Drivers!$B$5*Drivers!$B$6*Drivers!$B$7)*(B$5-Drivers!$B$9)+$A10*Drivers!$B$10+Drivers!$B$11*Drivers!$B$12-Drivers!$B$15-ROUNDUP($A10/Drivers!$B$17,0)*Drivers!$B$16-Drivers!$B$18-Drivers!$B$19-Drivers!$B$20-Drivers!$B$21 -> 37925 | C10: =($A10*Drivers!$B$5*Drivers!$B$6*Drivers!$B$7)*(C$5-Drivers!$B$9)+$A10*Drivers!$B$10+Drivers!$B$11*Drivers!$B$12-Drivers!$B$15-ROUNDUP($A10/Drivers!$B$17,0)*Drivers!$B$16-Drivers!$B$18-Drivers!$B$19-Drivers!$B$20-Drivers!$B$21 -> 62300 | D10: =($A10*Drivers!$B$5*Drivers!$B$6*Drivers!$B$7)*(D$5-Drivers!$B$9)+$A10*Drivers!$B$10+Drivers!$B$11*Drivers!$B$12-Drivers!$B$15-ROUNDUP($A10/Drivers!$B$17,0)*Drivers!$B$16-Drivers!$B$18-Drivers!$B$19-Drivers!$B$20-Drivers!$B$21 -> 86675 | E10: =($A10*Drivers!$B$5*Drivers!$B$6*Drivers!$B$7)*(E$5-Drivers!$B$9)+$A10*Drivers!$B$10+Drivers!$B$11*Drivers!$B$12-Drivers!$B$15-ROUNDUP($A10/Drivers!$B$17,0)*Drivers!$B$16-Drivers!$B$18-Drivers!$B$19-Drivers!$B$20-Drivers!$B$21 -> 135425 | F10: =($A10*Drivers!$B$5*Drivers!$B$6*Drivers!$B$7)*(F$5-Drivers!$B$9)+$A10*Drivers!$B$10+Drivers!$B$11*Drivers!$B$12-Drivers!$B$15-ROUNDUP($A10/Drivers!$B$17,0)*Drivers!$B$16-Drivers!$B$18-Drivers!$B$19-Drivers!$B$20-Drivers!$B$21 -> 184175
A11: 400 | B11: =($A11*Drivers!$B$5*Drivers!$B$6*Drivers!$B$7)*(B$5-Drivers!$B$9)+$A11*Drivers!$B$10+Drivers!$B$11*Drivers!$B$12-Drivers!$B$15-ROUNDUP($A11/Drivers!$B$17,0)*Drivers!$B$16-Drivers!$B$18-Drivers!$B$19-Drivers!$B$20-Drivers!$B$21 -> 74960 | C11: =($A11*Drivers!$B$5*Drivers!$B$6*Drivers!$B$7)*(C$5-Drivers!$B$9)+$A11*Drivers!$B$10+Drivers!$B$11*Drivers!$B$12-Drivers!$B$15-ROUNDUP($A11/Drivers!$B$17,0)*Drivers!$B$16-Drivers!$B$18-Drivers!$B$19-Drivers!$B$20-Drivers!$B$21 -> 113960 | D11: =($A11*Drivers!$B$5*Drivers!$B$6*Drivers!$B$7)*(D$5-Drivers!$B$9)+$A11*Drivers!$B$10+Drivers!$B$11*Drivers!$B$12-Drivers!$B$15-ROUNDUP($A11/Drivers!$B$17,0)*Drivers!$B$16-Drivers!$B$18-Drivers!$B$19-Drivers!$B$20-Drivers!$B$21 -> 152960 | E11: =($A11*Drivers!$B$5*Drivers!$B$6*Drivers!$B$7)*(E$5-Drivers!$B$9)+$A11*Drivers!$B$10+Drivers!$B$11*Drivers!$B$12-Drivers!$B$15-ROUNDUP($A11/Drivers!$B$17,0)*Drivers!$B$16-Drivers!$B$18-Drivers!$B$19-Drivers!$B$20-Drivers!$B$21 -> 230960 | F11: =($A11*Drivers!$B$5*Drivers!$B$6*Drivers!$B$7)*(F$5-Drivers!$B$9)+$A11*Drivers!$B$10+Drivers!$B$11*Drivers!$B$12-Drivers!$B$15-ROUNDUP($A11/Drivers!$B$17,0)*Drivers!$B$16-Drivers!$B$18-Drivers!$B$19-Drivers!$B$20-Drivers!$B$21 -> 308960
A14: GRID B - Platform monthly profit: Number of venues (rows) x Monthly booking rate (cols)
A15: Venues \ Booking rate | B15: 0.06 | C15: 0.08 | D15: 0.1 | E15: 0.12 | F15: 0.15
A16: 25 | B16: =($A16*Drivers!$B$5*B$15*Drivers!$B$7)*(Drivers!$B$8-Drivers!$B$9)+$A16*Drivers!$B$10+Drivers!$B$11*Drivers!$B$12-Drivers!$B$15-ROUNDUP($A16/Drivers!$B$17,0)*Drivers!$B$16-Drivers!$B$18-Drivers!$B$19-Drivers!$B$20-Drivers!$B$21 -> -14471.5 | C16: =($A16*Drivers!$B$5*C$15*Drivers!$B$7)*(Drivers!$B$8-Drivers!$B$9)+$A16*Drivers!$B$10+Drivers!$B$11*Drivers!$B$12-Drivers!$B$15-ROUNDUP($A16/Drivers!$B$17,0)*Drivers!$B$16-Drivers!$B$18-Drivers!$B$19-Drivers!$B$20-Drivers!$B$21 -> -12112 | D16: =($A16*Drivers!$B$5*D$15*Drivers!$B$7)*(Drivers!$B$8-Drivers!$B$9)+$A16*Drivers!$B$10+Drivers!$B$11*Drivers!$B$12-Drivers!$B$15-ROUNDUP($A16/Drivers!$B$17,0)*Drivers!$B$16-Drivers!$B$18-Drivers!$B$19-Drivers!$B$20-Drivers!$B$21 -> -9752.5 | E16: =($A16*Drivers!$B$5*E$15*Drivers!$B$7)*(Drivers!$B$8-Drivers!$B$9)+$A16*Drivers!$B$10+Drivers!$B$11*Drivers!$B$12-Drivers!$B$15-ROUNDUP($A16/Drivers!$B$17,0)*Drivers!$B$16-Drivers!$B$18-Drivers!$B$19-Drivers!$B$20-Drivers!$B$21 -> -7393 | F16: =($A16*Drivers!$B$5*F$15*Drivers!$B$7)*(Drivers!$B$8-Drivers!$B$9)+$A16*Drivers!$B$10+Drivers!$B$11*Drivers!$B$12-Drivers!$B$15-ROUNDUP($A16/Drivers!$B$17,0)*Drivers!$B$16-Drivers!$B$18-Drivers!$B$19-Drivers!$B$20-Drivers!$B$21 -> -3853.75
A17: 50 | B17: =($A17*Drivers!$B$5*B$15*Drivers!$B$7)*(Drivers!$B$8-Drivers!$B$9)+$A17*Drivers!$B$10+Drivers!$B$11*Drivers!$B$12-Drivers!$B$15-ROUNDUP($A17/Drivers!$B$17,0)*Drivers!$B$16-Drivers!$B$18-Drivers!$B$19-Drivers!$B$20-Drivers!$B$21 -> -7143 | C17: =($A17*Drivers!$B$5*C$15*Drivers!$B$7)*(Drivers!$B$8-Drivers!$B$9)+$A17*Drivers!$B$10+Drivers!$B$11*Drivers!$B$12-Drivers!$B$15-ROUNDUP($A17/Drivers!$B$17,0)*Drivers!$B$16-Drivers!$B$18-Drivers!$B$19-Drivers!$B$20-Drivers!$B$21 -> -2424 | D17: =($A17*Drivers!$B$5*D$15*Drivers!$B$7)*(Drivers!$B$8-Drivers!$B$9)+$A17*Drivers!$B$10+Drivers!$B$11*Drivers!$B$12-Drivers!$B$15-ROUNDUP($A17/Drivers!$B$17,0)*Drivers!$B$16-Drivers!$B$18-Drivers!$B$19-Drivers!$B$20-Drivers!$B$21 -> 2295 | E17: =($A17*Drivers!$B$5*E$15*Drivers!$B$7)*(Drivers!$B$8-Drivers!$B$9)+$A17*Drivers!$B$10+Drivers!$B$11*Drivers!$B$12-Drivers!$B$15-ROUNDUP($A17/Drivers!$B$17,0)*Drivers!$B$16-Drivers!$B$18-Drivers!$B$19-Drivers!$B$20-Drivers!$B$21 -> 7014 | F17: =($A17*Drivers!$B$5*F$15*Drivers!$B$7)*(Drivers!$B$8-Drivers!$B$9)+$A17*Drivers!$B$10+Drivers!$B$11*Drivers!$B$12-Drivers!$B$15-ROUNDUP($A17/Drivers!$B$17,0)*Drivers!$B$16-Drivers!$B$18-Drivers!$B$19-Drivers!$B$20-Drivers!$B$21 -> 14092.5
A18: 100 | B18: =($A18*Drivers!$B$5*B$15*Drivers!$B$7)*(Drivers!$B$8-Drivers!$B$9)+$A18*Drivers!$B$10+Drivers!$B$11*Drivers!$B$12-Drivers!$B$15-ROUNDUP($A18/Drivers!$B$17,0)*Drivers!$B$16-Drivers!$B$18-Drivers!$B$19-Drivers!$B$20-Drivers!$B$21 -> 7514 | C18: =($A18*Drivers!$B$5*C$15*Drivers!$B$7)*(Drivers!$B$8-Drivers!$B$9)+$A18*Drivers!$B$10+Drivers!$B$11*Drivers!$B$12-Drivers!$B$15-ROUNDUP($A18/Drivers!$B$17,0)*Drivers!$B$16-Drivers!$B$18-Drivers!$B$19-Drivers!$B$20-Drivers!$B$21 -> 16952 | D18: =($A18*Drivers!$B$5*D$15*Drivers!$B$7)*(Drivers!$B$8-Drivers!$B$9)+$A18*Drivers!$B$10+Drivers!$B$11*Drivers!$B$12-Drivers!$B$15-ROUNDUP($A18/Drivers!$B$17,0)*Drivers!$B$16-Drivers!$B$18-Drivers!$B$19-Drivers!$B$20-Drivers!$B$21 -> 26390 | E18: =($A18*Drivers!$B$5*E$15*Drivers!$B$7)*(Drivers!$B$8-Drivers!$B$9)+$A18*Drivers!$B$10+Drivers!$B$11*Drivers!$B$12-Drivers!$B$15-ROUNDUP($A18/Drivers!$B$17,0)*Drivers!$B$16-Drivers!$B$18-Drivers!$B$19-Drivers!$B$20-Drivers!$B$21 -> 35828 | F18: =($A18*Drivers!$B$5*F$15*Drivers!$B$7)*(Drivers!$B$8-Drivers!$B$9)+$A18*Drivers!$B$10+Drivers!$B$11*Drivers!$B$12-Drivers!$B$15-ROUNDUP($A18/Drivers!$B$17,0)*Drivers!$B$16-Drivers!$B$18-Drivers!$B$19-Drivers!$B$20-Drivers!$B$21 -> 49985
A19: 150 | B19: =($A19*Drivers!$B$5*B$15*Drivers!$B$7)*(Drivers!$B$8-Drivers!$B$9)+$A19*Drivers!$B$10+Drivers!$B$11*Drivers!$B$12-Drivers!$B$15-ROUNDUP($A19/Drivers!$B$17,0)*Drivers!$B$16-Drivers!$B$18-Drivers!$B$19-Drivers!$B$20-Drivers!$B$21 -> 16171 | C19: =($A19*Drivers!$B$5*C$15*Drivers!$B$7)*(Drivers!$B$8-Drivers!$B$9)+$A19*Drivers!$B$10+Drivers!$B$11*Drivers!$B$12-Drivers!$B$15-ROUNDUP($A19/Drivers!$B$17,0)*Drivers!$B$16-Drivers!$B$18-Drivers!$B$19-Drivers!$B$20-Drivers!$B$21 -> 30328 | D19: =($A19*Drivers!$B$5*D$15*Drivers!$B$7)*(Drivers!$B$8-Drivers!$B$9)+$A19*Drivers!$B$10+Drivers!$B$11*Drivers!$B$12-Drivers!$B$15-ROUNDUP($A19/Drivers!$B$17,0)*Drivers!$B$16-Drivers!$B$18-Drivers!$B$19-Drivers!$B$20-Drivers!$B$21 -> 44485 | E19: =($A19*Drivers!$B$5*E$15*Drivers!$B$7)*(Drivers!$B$8-Drivers!$B$9)+$A19*Drivers!$B$10+Drivers!$B$11*Drivers!$B$12-Drivers!$B$15-ROUNDUP($A19/Drivers!$B$17,0)*Drivers!$B$16-Drivers!$B$18-Drivers!$B$19-Drivers!$B$20-Drivers!$B$21 -> 58642 | F19: =($A19*Drivers!$B$5*F$15*Drivers!$B$7)*(Drivers!$B$8-Drivers!$B$9)+$A19*Drivers!$B$10+Drivers!$B$11*Drivers!$B$12-Drivers!$B$15-ROUNDUP($A19/Drivers!$B$17,0)*Drivers!$B$16-Drivers!$B$18-Drivers!$B$19-Drivers!$B$20-Drivers!$B$21 -> 79877.5
A20: 250 | B20: =($A20*Drivers!$B$5*B$15*Drivers!$B$7)*(Drivers!$B$8-Drivers!$B$9)+$A20*Drivers!$B$10+Drivers!$B$11*Drivers!$B$12-Drivers!$B$15-ROUNDUP($A20/Drivers!$B$17,0)*Drivers!$B$16-Drivers!$B$18-Drivers!$B$19-Drivers!$B$20-Drivers!$B$21 -> 39485 | C20: =($A20*Drivers!$B$5*C$15*Drivers!$B$7)*(Drivers!$B$8-Drivers!$B$9)+$A20*Drivers!$B$10+Drivers!$B$11*Drivers!$B$12-Drivers!$B$15-ROUNDUP($A20/Drivers!$B$17,0)*Drivers!$B$16-Drivers!$B$18-Drivers!$B$19-Drivers!$B$20-Drivers!$B$21 -> 63080 | D20: =($A20*Drivers!$B$5*D$15*Drivers!$B$7)*(Drivers!$B$8-Drivers!$B$9)+$A20*Drivers!$B$10+Drivers!$B$11*Drivers!$B$12-Drivers!$B$15-ROUNDUP($A20/Drivers!$B$17,0)*Drivers!$B$16-Drivers!$B$18-Drivers!$B$19-Drivers!$B$20-Drivers!$B$21 -> 86675 | E20: =($A20*Drivers!$B$5*E$15*Drivers!$B$7)*(Drivers!$B$8-Drivers!$B$9)+$A20*Drivers!$B$10+Drivers!$B$11*Drivers!$B$12-Drivers!$B$15-ROUNDUP($A20/Drivers!$B$17,0)*Drivers!$B$16-Drivers!$B$18-Drivers!$B$19-Drivers!$B$20-Drivers!$B$21 -> 110270 | F20: =($A20*Drivers!$B$5*F$15*Drivers!$B$7)*(Drivers!$B$8-Drivers!$B$9)+$A20*Drivers!$B$10+Drivers!$B$11*Drivers!$B$12-Drivers!$B$15-ROUNDUP($A20/Drivers!$B$17,0)*Drivers!$B$16-Drivers!$B$18-Drivers!$B$19-Drivers!$B$20-Drivers!$B$21 -> 145662.5
A21: 400 | B21: =($A21*Drivers!$B$5*B$15*Drivers!$B$7)*(Drivers!$B$8-Drivers!$B$9)+$A21*Drivers!$B$10+Drivers!$B$11*Drivers!$B$12-Drivers!$B$15-ROUNDUP($A21/Drivers!$B$17,0)*Drivers!$B$16-Drivers!$B$18-Drivers!$B$19-Drivers!$B$20-Drivers!$B$21 -> 77456 | C21: =($A21*Drivers!$B$5*C$15*Drivers!$B$7)*(Drivers!$B$8-Drivers!$B$9)+$A21*Drivers!$B$10+Drivers!$B$11*Drivers!$B$12-Drivers!$B$15-ROUNDUP($A21/Drivers!$B$17,0)*Drivers!$B$16-Drivers!$B$18-Drivers!$B$19-Drivers!$B$20-Drivers!$B$21 -> 115208 | D21: =($A21*Drivers!$B$5*D$15*Drivers!$B$7)*(Drivers!$B$8-Drivers!$B$9)+$A21*Drivers!$B$10+Drivers!$B$11*Drivers!$B$12-Drivers!$B$15-ROUNDUP($A21/Drivers!$B$17,0)*Drivers!$B$16-Drivers!$B$18-Drivers!$B$19-Drivers!$B$20-Drivers!$B$21 -> 152960 | E21: =($A21*Drivers!$B$5*E$15*Drivers!$B$7)*(Drivers!$B$8-Drivers!$B$9)+$A21*Drivers!$B$10+Drivers!$B$11*Drivers!$B$12-Drivers!$B$15-ROUNDUP($A21/Drivers!$B$17,0)*Drivers!$B$16-Drivers!$B$18-Drivers!$B$19-Drivers!$B$20-Drivers!$B$21 -> 190712 | F21: =($A21*Drivers!$B$5*F$15*Drivers!$B$7)*(Drivers!$B$8-Drivers!$B$9)+$A21*Drivers!$B$10+Drivers!$B$11*Drivers!$B$12-Drivers!$B$15-ROUNDUP($A21/Drivers!$B$17,0)*Drivers!$B$16-Drivers!$B$18-Drivers!$B$19-Drivers!$B$20-Drivers!$B$21 -> 247340
A23: Operator profit for comparison (crews per Drivers): | E23: ='Operator vs Platform'!B7 -> 36030
A24: Compare grid cells to this figure to see which venue counts beat the operator.
